<?xml version="1.0" encoding="utf-8"?>
<!DOCTYPE hibernate-mapping PUBLIC "-//Hibernate/Hibernate Mapping DTD 3.0//EN"
"http://hibernate.sourceforge.net/hibernate-mapping-3.0.dtd">
<!-- 
    Mapping file autogenerated by MyEclipse Persistence Tools
-->
<hibernate-mapping>
    <class name="org.view.VComment" table="v_comment" catalog="tendaehome">
        <composite-id name="id" class="org.view.VCommentId">
            <key-property name="id" type="java.lang.Long">
                <column name="id" />
            </key-property>
            <key-property name="description" type="java.lang.String">
                <column name="description" length="200" />
            </key-property>
            <key-property name="rating" type="java.lang.Integer">
                <column name="rating" />
            </key-property>
            <key-property name="userid" type="java.lang.Long">
                <column name="userid" />
            </key-property>
            <key-property name="orderId" type="java.lang.Long">
                <column name="order_id" />
            </key-property>
            <key-property name="isVisable" type="java.lang.Integer">
                <column name="is_visable" />
            </key-property>
            <key-property name="time" type="java.sql.Timestamp">
                <column name="time" length="19" />
            </key-property>
            <key-property name="reply" type="java.lang.String">
                <column name="reply" />
            </key-property>
            <key-property name="headImg" type="java.lang.String">
                <column name="head_img" length="236" />
            </key-property>
            <key-property name="catalogId" type="java.lang.Integer">
                <column name="catalog_id" />
            </key-property>
            <key-property name="franchiseeName" type="java.lang.String">
                <column name="franchisee_name" length="20" />
            </key-property>
            <key-property name="nickname" type="java.lang.String">
                <column name="nickname" length="20" />
            </key-property>
            <key-property name="imgUrl" type="java.lang.String">
                <column name="img_url" length="341" />
            </key-property>
        </composite-id>
    </class>
</hibernate-mapping>
